odoo/addons/so_line_description_without_internal_ref/README.rst
odoo/addons/so_line_description_without_internal_ref/__init__.py
odoo/addons/so_line_description_without_internal_ref/__manifest__.py
odoo/addons/so_line_description_without_internal_ref/models/__init__.py
odoo/addons/so_line_description_without_internal_ref/models/product.py
odoo/addons/so_line_description_without_internal_ref/models/sale_order_line.py
odoo/addons/so_line_description_without_internal_ref/static/description/icon.png
odoo_addon_so_line_description_without_internal_ref-15.0.1.0.1.dist-info/METADATA
odoo_addon_so_line_description_without_internal_ref-15.0.1.0.1.dist-info/WHEEL
odoo_addon_so_line_description_without_internal_ref-15.0.1.0.1.dist-info/top_level.txt
odoo_addon_so_line_description_without_internal_ref-15.0.1.0.1.dist-info/RECORD
